{
  "AuthenticateEndpointsWith": [
    {
      "AuthenticationToApply": {
        "AuthenticationSchemeName": "furkot_auth_access_code",
        "RequiredScopes": [
          "readtrips"
        ]
      },
      "OptionType": "Single",
      "Description": ""
    },
    {
      "AuthenticationToApply": {
        "AuthenticationSchemeName": "furkot_auth_implicit",
        "RequiredScopes": [
          "readtrips"
        ]
      },
      "OptionType": "Single",
      "Description": ""
    }
  ],
  "Name": "Furkot Trips",
  "BaseUri": "https://trips.furkot.com/pub/api",
  "ServerConfiguration": {
    "UseParent": false,
    "DefaultEnvironment": "production",
    "DefaultServer": "default",
    "Environments": [
      {
        "Name": "production",
        "Servers": [
          {
            "Name": "default",
            "Url": "https://trips.furkot.com/pub/api",
            "Parameters": []
          },
          {
            "Name": "auth server",
            "Url": "https://trips.furkot.com/oauth",
            "Parameters": []
          }
        ],
        "DisableTryItOut": false
      }
    ],
    "Parameters": []
  },
  "Description": "Furkot provides Rest API to access user trip data.\nUsing Furkot API an application can list user trips and display stops for a specific trip.\nFurkot API uses OAuth2 protocol to authorize applications to access data on behalf of users.\n",
  "Version": "1.0.0",
  "Contact": {
    "Email": "trips@furkot.com"
  },
  "AdditionalHeaders": [],
  "Authentication": {
    "Type": "OAuth_v2_WebServerFlow",
    "AuthType": "OAuth_v2_WebServerFlow",
    "Parameters": [],
    "AuthorizationUrl": "/authorize",
    "AccessTokenUrl": "/access_token",
    "OAuth2AuthorizationServer": "auth server",
    "Scopes": [
      {
        "Name": "readtrips",
        "Value": "read:trips",
        "Description": "list trips and stops info"
      }
    ],
    "ParamFormats": {},
    "AllowAdditionalOAuthFields": false,
    "AdditionalOAuthFields": []
  },
  "AuthenticationSchemes": {
    "furkot_auth_access_code": {
      "AuthenticationType": "OAuth_v2_WebServerFlow",
      "Parameters": [],
      "OAuthInfo": {
        "AuthorizationUrl": "/authorize",
        "AccessTokenUrl": "/access_token",
        "OAuth2AuthorizationServer": "auth server",
        "Scopes": [
          {
            "Name": "readtrips",
            "Value": "read:trips",
            "Description": "list trips and stops info"
          }
        ],
        "ParamFormats": {},
        "AllowAdditionalOAuthFields": false,
        "AdditionalOAuthFields": []
      }
    },
    "furkot_auth_implicit": {
      "AuthenticationType": "OAuth_v2_ImplicitGrantFlow_UserAgent",
      "Parameters": [],
      "OAuthInfo": {
        "AuthorizationUrl": "/authorize",
        "OAuth2AuthorizationServer": "auth server",
        "Scopes": [
          {
            "Name": "readtrips",
            "Value": "read:trips",
            "Description": "list users trips info"
          }
        ],
        "ParamFormats": {},
        "AllowAdditionalOAuthFields": false,
        "AdditionalOAuthFields": []
      }
    }
  },
  "Endpoints": [
    {
      "AuthenticateEndpointWith": [],
      "Name": "Trip_GET",
      "Description": "list user's trips",
      "HTTPMethod": "GET",
      "RequiresAuthentication": true,
      "Route": "/trip",
      "Responses": {
        "200": {
          "Name": "response",
          "Description": "Successful response",
          "Headers": [],
          "BodyContent": {
            "application/json": {
              "AnyOfTypes": [],
              "AnyOfCasesMeta": [],
              "OneOfTypes": [],
              "OneOfCasesMeta": [],
              "NotTypes": [],
              "NotCasesMeta": [],
              "Type": "Trip",
              "IsSdlNativeType": false,
              "Constant": false,
              "IsNullDefaultExplicit": false,
              "IsNullExampleExplicit": false,
              "Examples": [],
              "Nullable": false,
              "NullableArrayItems": false,
              "NullableMapValues": false,
              "IsArray": true,
              "IsMap": false,
              "IsArrayOfMap": false
            }
          }
        }
      },
      "Response": {
        "Optional": false,
        "AnyOfTypes": [],
        "AnyOfCasesMeta": [],
        "OneOfTypes": [],
        "OneOfCasesMeta": [],
        "NotTypes": [],
        "NotCasesMeta": [],
        "Type": "Trip",
        "IsSdlNativeType": false,
        "Constant": false,
        "IsStream": false,
        "IsAttribute": false,
        "IsNullExampleExplicit": false,
        "Examples": [],
        "Nullable": false,
        "NullableArrayItems": false,
        "NullableMapValues": false,
        "ReadOnly": false,
        "WriteOnly": false,
        "IsArray": true,
        "IsMap": false,
        "IsArrayOfMap": false,
        "Deprecated": false,
        "Name": "response",
        "Description": "Successful response",
        "IsNullDefaultExplicit": false
      },
      "ResponseCode": 200,
      "ResponseHeaders": [
        {
          "Optional": false,
          "AnyOfTypes": [],
          "AnyOfCasesMeta": [],
          "OneOfTypes": [],
          "OneOfCasesMeta": [],
          "NotTypes": [],
          "NotCasesMeta": [],
          "Type": "String",
          "IsSdlNativeType": true,
          "Constant": false,
          "IsStream": false,
          "IsAttribute": false,
          "IsNullExampleExplicit": false,
          "Examples": [],
          "Attributes": {},
          "Nullable": false,
          "NullableArrayItems": false,
          "NullableMapValues": false,
          "ReadOnly": false,
          "WriteOnly": false,
          "IsArray": false,
          "IsMap": false,
          "IsArrayOfMap": false,
          "Deprecated": false,
          "Name": "Content-Type",
          "DefaultValue": "application/json",
          "IsNullDefaultExplicit": false
        }
      ],
      "ResponseContentType": "application/json",
      "HasOptionalQueryParams": false,
      "HasOptionalFieldParams": false,
      "CollectParameters": false,
      "RequiredScopes": [
        "readtrips"
      ],
      "Parameters": [],
      "Errors": [],
      "TestCases": [],
      "WrapBodyInObject": false,
      "Deprecated": false,
      "XmlRequest": false,
      "XmlResponse": false,
      "ErrorTemplates": {},
      "SkipAdditionalHeaders": false,
      "Callbacks": []
    },
    {
      "AuthenticateEndpointWith": [],
      "Name": "TripStopByTripId_GET",
      "Description": "list stops for a trip identified by {trip_id}",
      "HTTPMethod": "GET",
      "RequiresAuthentication": true,
      "Route": "/trip/{trip_id}/stop",
      "Responses": {
        "200": {
          "Name": "response",
          "Description": "Successful response",
          "Headers": [],
          "BodyContent": {
            "application/json": {
              "AnyOfTypes": [],
              "AnyOfCasesMeta": [],
              "OneOfTypes": [],
              "OneOfCasesMeta": [],
              "NotTypes": [],
              "NotCasesMeta": [],
              "Type": "Step",
              "IsSdlNativeType": false,
              "Constant": false,
              "IsNullDefaultExplicit": false,
              "IsNullExampleExplicit": false,
              "Examples": [],
              "Nullable": false,
              "NullableArrayItems": false,
              "NullableMapValues": false,
              "IsArray": true,
              "IsMap": false,
              "IsArrayOfMap": false
            }
          }
        }
      },
      "Response": {
        "Optional": false,
        "AnyOfTypes": [],
        "AnyOfCasesMeta": [],
        "OneOfTypes": [],
        "OneOfCasesMeta": [],
        "NotTypes": [],
        "NotCasesMeta": [],
        "Type": "Step",
        "IsSdlNativeType": false,
        "Constant": false,
        "IsStream": false,
        "IsAttribute": false,
        "IsNullExampleExplicit": false,
        "Examples": [],
        "Nullable": false,
        "NullableArrayItems": false,
        "NullableMapValues": false,
        "ReadOnly": false,
        "WriteOnly": false,
        "IsArray": true,
        "IsMap": false,
        "IsArrayOfMap": false,
        "Deprecated": false,
        "Name": "response",
        "Description": "Successful response",
        "IsNullDefaultExplicit": false
      },
      "ResponseCode": 200,
      "ResponseHeaders": [
        {
          "Optional": false,
          "AnyOfTypes": [],
          "AnyOfCasesMeta": [],
          "OneOfTypes": [],
          "OneOfCasesMeta": [],
          "NotTypes": [],
          "NotCasesMeta": [],
          "Type": "String",
          "IsSdlNativeType": true,
          "Constant": false,
          "IsStream": false,
          "IsAttribute": false,
          "IsNullExampleExplicit": false,
          "Examples": [],
          "Attributes": {},
          "Nullable": false,
          "NullableArrayItems": false,
          "NullableMapValues": false,
          "ReadOnly": false,
          "WriteOnly": false,
          "IsArray": false,
          "IsMap": false,
          "IsArrayOfMap": false,
          "Deprecated": false,
          "Name": "Content-Type",
          "DefaultValue": "application/json",
          "IsNullDefaultExplicit": false
        }
      ],
      "ResponseContentType": "application/json",
      "HasOptionalQueryParams": false,
      "HasOptionalFieldParams": false,
      "CollectParameters": false,
      "RequiredScopes": [
        "readtrips"
      ],
      "Parameters": [
        {
          "ParamFormat": "Template",
          "AutoGeneratedOrModified": false,
          "Optional": false,
          "AnyOfTypes": [],
          "AnyOfCasesMeta": [],
          "OneOfTypes": [],
          "OneOfCasesMeta": [],
          "NotTypes": [],
          "NotCasesMeta": [],
          "Type": "String",
          "IsSdlNativeType": true,
          "Constant": false,
          "IsStream": false,
          "IsAttribute": false,
          "IsNullExampleExplicit": false,
          "Examples": [],
          "Attributes": {},
          "Nullable": false,
          "NullableArrayItems": false,
          "NullableMapValues": false,
          "ReadOnly": false,
          "WriteOnly": false,
          "IsArray": false,
          "IsMap": false,
          "IsArrayOfMap": false,
          "Deprecated": false,
          "Name": "trip_id",
          "Description": "id of the trip",
          "IsNullDefaultExplicit": false
        }
      ],
      "Errors": [],
      "TestCases": [],
      "WrapBodyInObject": false,
      "Deprecated": false,
      "XmlRequest": false,
      "XmlResponse": false,
      "ErrorTemplates": {},
      "SkipAdditionalHeaders": false,
      "Callbacks": []
    }
  ],
  "Webhooks": [],
  "WebhookGroups": {},
  "CallbackGroups": {},
  "EndpointGroups": [],
  "CustomTypes": [
    {
      "Name": "Step",
      "ImplementationType": "Structure",
      "Fields": [
        {
          "Optional": true,
          "AnyOfTypes": [],
          "AnyOfCasesMeta": [],
          "OneOfTypes": [],
          "OneOfCasesMeta": [],
          "NotTypes": [],
          "NotCasesMeta": [],
          "Type": "String",
          "IsSdlNativeType": true,
          "IsTypeJsonObject": false,
          "Constant": false,
          "IsStream": false,
          "IsAttribute": false,
          "IsNullExampleExplicit": false,
          "Examples": [],
          "Attributes": {},
          "Nullable": false,
          "NullableArrayItems": false,
          "NullableMapValues": false,
          "ReadOnly": false,
          "WriteOnly": false,
          "IsArray": false,
          "IsMap": false,
          "IsArrayOfMap": false,
          "Deprecated": false,
          "Name": "address",
          "Description": "address of the stop",
          "IsNullDefaultExplicit": false
        },
        {
          "Optional": true,
          "AnyOfTypes": [],
          "AnyOfCasesMeta": [],
          "OneOfTypes": [],
          "OneOfCasesMeta": [],
          "NotTypes": [],
          "NotCasesMeta": [],
          "Type": "DateTime",
          "IsSdlNativeType": true,
          "IsTypeJsonObject": false,
          "Constant": false,
          "IsStream": false,
          "IsAttribute": false,
          "IsNullExampleExplicit": false,
          "Examples": [],
          "Attributes": {
            "Format": "Rfc3339"
          },
          "Nullable": false,
          "NullableArrayItems": false,
          "NullableMapValues": false,
          "ReadOnly": false,
          "WriteOnly": false,
          "IsArray": false,
          "IsMap": false,
          "IsArrayOfMap": false,
          "Deprecated": false,
          "Name": "arrival",
          "Description": "arrival at the stop in its local timezone as YYYY-MM-DDThh:mm",
          "IsNullDefaultExplicit": false
        },
        {
          "Optional": true,
          "AnyOfTypes": [],
          "AnyOfCasesMeta": [],
          "OneOfTypes": [],
          "OneOfCasesMeta": [],
          "NotTypes": [],
          "NotCasesMeta": [],
          "Type": "Coordinates",
          "IsSdlNativeType": false,
          "Constant": false,
          "IsStream": false,
          "IsAttribute": false,
          "IsNullExampleExplicit": false,
          "Examples": [],
          "Nullable": false,
          "NullableArrayItems": false,
          "NullableMapValues": false,
          "ReadOnly": false,
          "WriteOnly": false,
          "IsArray": false,
          "IsMap": false,
          "IsArrayOfMap": false,
          "Deprecated": false,
          "Name": "coordinates",
          "Description": "geographical coordinates of the stop",
          "IsNullDefaultExplicit": false
        },
        {
          "Optional": true,
          "AnyOfTypes": [],
          "AnyOfCasesMeta": [],
          "OneOfTypes": [],
          "OneOfCasesMeta": [],
          "NotTypes": [],
          "NotCasesMeta": [],
          "Type": "DateTime",
          "IsSdlNativeType": true,
          "IsTypeJsonObject": false,
          "Constant": false,
          "IsStream": false,
          "IsAttribute": false,
          "IsNullExampleExplicit": false,
          "Examples": [],
          "Attributes": {
            "Format": "Rfc3339"
          },
          "Nullable": false,
          "NullableArrayItems": false,
          "NullableMapValues": false,
          "ReadOnly": false,
          "WriteOnly": false,
          "IsArray": false,
          "IsMap": false,
          "IsArrayOfMap": false,
          "Deprecated": false,
          "Name": "departure",
          "Description": "departure from the stop in its local timezone as YYYY-MM-DDThh:mm",
          "IsNullDefaultExplicit": false
        },
        {
          "Optional": true,
          "AnyOfTypes": [],
          "AnyOfCasesMeta": [],
          "OneOfTypes": [],
          "OneOfCasesMeta": [],
          "NotTypes": [],
          "NotCasesMeta": [],
          "Type": "String",
          "IsSdlNativeType": true,
          "IsTypeJsonObject": false,
          "Constant": false,
          "IsStream": false,
          "IsAttribute": false,
          "IsNullExampleExplicit": false,
          "Examples": [],
          "Attributes": {},
          "Nullable": false,
          "NullableArrayItems": false,
          "NullableMapValues": false,
          "ReadOnly": false,
          "WriteOnly": false,
          "IsArray": false,
          "IsMap": false,
          "IsArrayOfMap": false,
          "Deprecated": false,
          "Name": "name",
          "Description": "name of the stop",
          "IsNullDefaultExplicit": false
        },
        {
          "Optional": true,
          "AnyOfTypes": [],
          "AnyOfCasesMeta": [],
          "OneOfTypes": [],
          "OneOfCasesMeta": [],
          "NotTypes": [],
          "NotCasesMeta": [],
          "Type": "Long",
          "IsSdlNativeType": true,
          "IsTypeJsonObject": false,
          "Constant": false,
          "IsStream": false,
          "IsAttribute": false,
          "IsNullExampleExplicit": false,
          "Examples": [],
          "Attributes": {},
          "Nullable": false,
          "NullableArrayItems": false,
          "NullableMapValues": false,
          "ReadOnly": false,
          "WriteOnly": false,
          "IsArray": false,
          "IsMap": false,
          "IsArrayOfMap": false,
          "Deprecated": false,
          "Name": "nights",
          "Description": "number of nights",
          "IsNullDefaultExplicit": false
        },
        {
          "Optional": true,
          "AnyOfTypes": [],
          "AnyOfCasesMeta": [],
          "OneOfTypes": [],
          "OneOfCasesMeta": [],
          "NotTypes": [],
          "NotCasesMeta": [],
          "Type": "Boolean",
          "IsSdlNativeType": true,
          "IsTypeJsonObject": false,
          "Constant": false,
          "IsStream": false,
          "IsAttribute": false,
          "IsNullExampleExplicit": false,
          "Examples": [],
          "Nullable": false,
          "NullableArrayItems": false,
          "NullableMapValues": false,
          "ReadOnly": false,
          "WriteOnly": false,
          "IsArray": false,
          "IsMap": false,
          "IsArrayOfMap": false,
          "Deprecated": false,
          "Name": "passthru",
          "Description": "true for pass-through points anchoring route",
          "IsNullDefaultExplicit": false
        },
        {
          "Optional": true,
          "AnyOfTypes": [],
          "AnyOfCasesMeta": [],
          "OneOfTypes": [],
          "OneOfCasesMeta": [],
          "NotTypes": [],
          "NotCasesMeta": [],
          "Type": "Route",
          "IsSdlNativeType": false,
          "Constant": false,
          "IsStream": false,
          "IsAttribute": false,
          "IsNullExampleExplicit": false,
          "Examples": [],
          "Nullable": false,
          "NullableArrayItems": false,
          "NullableMapValues": false,
          "ReadOnly": false,
          "WriteOnly": false,
          "IsArray": false,
          "IsMap": false,
          "IsArrayOfMap": false,
          "Deprecated": false,
          "Name": "route",
          "Description": "route leading to the stop",
          "IsNullDefaultExplicit": false
        },
        {
          "Optional": true,
          "AnyOfTypes": [],
          "AnyOfCasesMeta": [],
          "OneOfTypes": [],
          "OneOfCasesMeta": [],
          "NotTypes": [],
          "NotCasesMeta": [],
          "Type": "String",
          "IsSdlNativeType": true,
          "IsTypeJsonObject": false,
          "Constant": false,
          "IsStream": false,
          "IsAttribute": false,
          "IsNullExampleExplicit": false,
          "Examples": [],
          "Attributes": {},
          "Nullable": false,
          "NullableArrayItems": false,
          "NullableMapValues": false,
          "ReadOnly": false,
          "WriteOnly": false,
          "IsArray": false,
          "IsMap": false,
          "IsArrayOfMap": false,
          "Deprecated": false,
          "Name": "url",
          "Description": "url of the page with more information about the stop",
          "IsNullDefaultExplicit": false
        }
      ],
      "IsNullExampleExplicit": false,
      "ExampleValues": [],
      "Deprecated": false,
      "IsXmlType": false,
      "AllowAdditionalFields": true
    },
    {
      "Name": "Trip",
      "ImplementationType": "Structure",
      "Fields": [
        {
          "Optional": true,
          "AnyOfTypes": [],
          "AnyOfCasesMeta": [],
          "OneOfTypes": [],
          "OneOfCasesMeta": [],
          "NotTypes": [],
          "NotCasesMeta": [],
          "Type": "DateTime",
          "IsSdlNativeType": true,
          "IsTypeJsonObject": false,
          "Constant": false,
          "IsStream": false,
          "IsAttribute": false,
          "IsNullExampleExplicit": false,
          "Examples": [],
          "Attributes": {
            "Format": "Rfc3339"
          },
          "Nullable": false,
          "NullableArrayItems": false,
          "NullableMapValues": false,
          "ReadOnly": false,
          "WriteOnly": false,
          "IsArray": false,
          "IsMap": false,
          "IsArrayOfMap": false,
          "Deprecated": false,
          "Name": "begin",
          "Description": "begin of the trip in its local timezone as YYYY-MM-DDThh:mm",
          "IsNullDefaultExplicit": false
        },
        {
          "Optional": true,
          "AnyOfTypes": [],
          "AnyOfCasesMeta": [],
          "OneOfTypes": [],
          "OneOfCasesMeta": [],
          "NotTypes": [],
          "NotCasesMeta": [],
          "Type": "String",
          "IsSdlNativeType": true,
          "IsTypeJsonObject": false,
          "Constant": false,
          "IsStream": false,
          "IsAttribute": false,
          "IsNullExampleExplicit": false,
          "Examples": [],
          "Attributes": {},
          "Nullable": false,
          "NullableArrayItems": false,
          "NullableMapValues": false,
          "ReadOnly": false,
          "WriteOnly": false,
          "IsArray": false,
          "IsMap": false,
          "IsArrayOfMap": false,
          "Deprecated": false,
          "Name": "description",
          "Description": "description of the trip (truncated to 200 characters)",
          "IsNullDefaultExplicit": false
        },
        {
          "Optional": true,
          "AnyOfTypes": [],
          "AnyOfCasesMeta": [],
          "OneOfTypes": [],
          "OneOfCasesMeta": [],
          "NotTypes": [],
          "NotCasesMeta": [],
          "Type": "DateTime",
          "IsSdlNativeType": true,
          "IsTypeJsonObject": false,
          "Constant": false,
          "IsStream": false,
          "IsAttribute": false,
          "IsNullExampleExplicit": false,
          "Examples": [],
          "Attributes": {
            "Format": "Rfc3339"
          },
          "Nullable": false,
          "NullableArrayItems": false,
          "NullableMapValues": false,
          "ReadOnly": false,
          "WriteOnly": false,
          "IsArray": false,
          "IsMap": false,
          "IsArrayOfMap": false,
          "Deprecated": false,
          "Name": "end",
          "Description": "end of the trip in its local timezone as YYYY-MM-DDThh:mm",
          "IsNullDefaultExplicit": false
        },
        {
          "Optional": true,
          "AnyOfTypes": [],
          "AnyOfCasesMeta": [],
          "OneOfTypes": [],
          "OneOfCasesMeta": [],
          "NotTypes": [],
          "NotCasesMeta": [],
          "Type": "String",
          "IsSdlNativeType": true,
          "IsTypeJsonObject": false,
          "Constant": false,
          "IsStream": false,
          "IsAttribute": false,
          "IsNullExampleExplicit": false,
          "Examples": [],
          "Attributes": {},
          "Nullable": false,
          "NullableArrayItems": false,
          "NullableMapValues": false,
          "ReadOnly": false,
          "WriteOnly": false,
          "IsArray": false,
          "IsMap": false,
          "IsArrayOfMap": false,
          "Deprecated": false,
          "Name": "id",
          "Description": "Unique ID of the trip",
          "IsNullDefaultExplicit": false
        },
        {
          "Optional": true,
          "AnyOfTypes": [],
          "AnyOfCasesMeta": [],
          "OneOfTypes": [],
          "OneOfCasesMeta": [],
          "NotTypes": [],
          "NotCasesMeta": [],
          "Type": "String",
          "IsSdlNativeType": true,
          "IsTypeJsonObject": false,
          "Constant": false,
          "IsStream": false,
          "IsAttribute": false,
          "IsNullExampleExplicit": false,
          "Examples": [],
          "Attributes": {},
          "Nullable": false,
          "NullableArrayItems": false,
          "NullableMapValues": false,
          "ReadOnly": false,
          "WriteOnly": false,
          "IsArray": false,
          "IsMap": false,
          "IsArrayOfMap": false,
          "Deprecated": false,
          "Name": "name",
          "Description": "name of the trip",
          "IsNullDefaultExplicit": false
        }
      ],
      "IsNullExampleExplicit": false,
      "ExampleValues": [],
      "Deprecated": false,
      "IsXmlType": false,
      "AllowAdditionalFields": true
    },
    {
      "Name": "Coordinates",
      "ImplementationType": "Structure",
      "Description": "geographical coordinates of the stop",
      "Fields": [
        {
          "Optional": true,
          "AnyOfTypes": [],
          "AnyOfCasesMeta": [],
          "OneOfTypes": [],
          "OneOfCasesMeta": [],
          "NotTypes": [],
          "NotCasesMeta": [],
          "Type": "Precision",
          "IsSdlNativeType": true,
          "IsTypeJsonObject": false,
          "Constant": false,
          "IsStream": false,
          "IsAttribute": false,
          "IsNullExampleExplicit": false,
          "Examples": [],
          "Attributes": {},
          "Nullable": false,
          "NullableArrayItems": false,
          "NullableMapValues": false,
          "ReadOnly": false,
          "WriteOnly": false,
          "IsArray": false,
          "IsMap": false,
          "IsArrayOfMap": false,
          "Deprecated": false,
          "Name": "lat",
          "Description": "latitude",
          "IsNullDefaultExplicit": false
        },
        {
          "Optional": true,
          "AnyOfTypes": [],
          "AnyOfCasesMeta": [],
          "OneOfTypes": [],
          "OneOfCasesMeta": [],
          "NotTypes": [],
          "NotCasesMeta": [],
          "Type": "Precision",
          "IsSdlNativeType": true,
          "IsTypeJsonObject": false,
          "Constant": false,
          "IsStream": false,
          "IsAttribute": false,
          "IsNullExampleExplicit": false,
          "Examples": [],
          "Attributes": {},
          "Nullable": false,
          "NullableArrayItems": false,
          "NullableMapValues": false,
          "ReadOnly": false,
          "WriteOnly": false,
          "IsArray": false,
          "IsMap": false,
          "IsArrayOfMap": false,
          "Deprecated": false,
          "Name": "lon",
          "Description": "longitude",
          "IsNullDefaultExplicit": false
        }
      ],
      "IsNullExampleExplicit": false,
      "ExampleValues": [],
      "Deprecated": false,
      "IsXmlType": false,
      "AllowAdditionalFields": true
    },
    {
      "Name": "Mode",
      "ImplementationType": "Enumeration",
      "Description": "travel mode",
      "Fields": [
        {
          "Optional": false,
          "AnyOfTypes": [],
          "AnyOfCasesMeta": [],
          "OneOfTypes": [],
          "OneOfCasesMeta": [],
          "NotTypes": [],
          "NotCasesMeta": [],
          "Type": "String",
          "IsSdlNativeType": true,
          "Constant": false,
          "IsStream": false,
          "IsAttribute": false,
          "IsNullExampleExplicit": false,
          "Examples": [],
          "Attributes": {},
          "Nullable": false,
          "NullableArrayItems": false,
          "NullableMapValues": false,
          "ReadOnly": false,
          "WriteOnly": false,
          "IsArray": false,
          "IsMap": false,
          "IsArrayOfMap": false,
          "Deprecated": false,
          "Name": "car",
          "Description": "",
          "DefaultValue": "car",
          "IsNullDefaultExplicit": false
        },
        {
          "Optional": false,
          "AnyOfTypes": [],
          "AnyOfCasesMeta": [],
          "OneOfTypes": [],
          "OneOfCasesMeta": [],
          "NotTypes": [],
          "NotCasesMeta": [],
          "Type": "String",
          "IsSdlNativeType": true,
          "Constant": false,
          "IsStream": false,
          "IsAttribute": false,
          "IsNullExampleExplicit": false,
          "Examples": [],
          "Attributes": {},
          "Nullable": false,
          "NullableArrayItems": false,
          "NullableMapValues": false,
          "ReadOnly": false,
          "WriteOnly": false,
          "IsArray": false,
          "IsMap": false,
          "IsArrayOfMap": false,
          "Deprecated": false,
          "Name": "motorcycle",
          "Description": "",
          "DefaultValue": "motorcycle",
          "IsNullDefaultExplicit": false
        },
        {
          "Optional": false,
          "AnyOfTypes": [],
          "AnyOfCasesMeta": [],
          "OneOfTypes": [],
          "OneOfCasesMeta": [],
          "NotTypes": [],
          "NotCasesMeta": [],
          "Type": "String",
          "IsSdlNativeType": true,
          "Constant": false,
          "IsStream": false,
          "IsAttribute": false,
          "IsNullExampleExplicit": false,
          "Examples": [],
          "Attributes": {},
          "Nullable": false,
          "NullableArrayItems": false,
          "NullableMapValues": false,
          "ReadOnly": false,
          "WriteOnly": false,
          "IsArray": false,
          "IsMap": false,
          "IsArrayOfMap": false,
          "Deprecated": false,
          "Name": "bicycle",
          "Description": "",
          "DefaultValue": "bicycle",
          "IsNullDefaultExplicit": false
        },
        {
          "Optional": false,
          "AnyOfTypes": [],
          "AnyOfCasesMeta": [],
          "OneOfTypes": [],
          "OneOfCasesMeta": [],
          "NotTypes": [],
          "NotCasesMeta": [],
          "Type": "String",
          "IsSdlNativeType": true,
          "Constant": false,
          "IsStream": false,
          "IsAttribute": false,
          "IsNullExampleExplicit": false,
          "Examples": [],
          "Attributes": {},
          "Nullable": false,
          "NullableArrayItems": false,
          "NullableMapValues": false,
          "ReadOnly": false,
          "WriteOnly": false,
          "IsArray": false,
          "IsMap": false,
          "IsArrayOfMap": false,
          "Deprecated": false,
          "Name": "walk",
          "Description": "",
          "DefaultValue": "walk",
          "IsNullDefaultExplicit": false
        },
        {
          "Optional": false,
          "AnyOfTypes": [],
          "AnyOfCasesMeta": [],
          "OneOfTypes": [],
          "OneOfCasesMeta": [],
          "NotTypes": [],
          "NotCasesMeta": [],
          "Type": "String",
          "IsSdlNativeType": true,
          "Constant": false,
          "IsStream": false,
          "IsAttribute": false,
          "IsNullExampleExplicit": false,
          "Examples": [],
          "Attributes": {},
          "Nullable": false,
          "NullableArrayItems": false,
          "NullableMapValues": false,
          "ReadOnly": false,
          "WriteOnly": false,
          "IsArray": false,
          "IsMap": false,
          "IsArrayOfMap": false,
          "Deprecated": false,
          "Name": "other",
          "Description": "",
          "DefaultValue": "other",
          "IsNullDefaultExplicit": false
        }
      ],
      "IsNullExampleExplicit": false,
      "ExampleValues": [],
      "Deprecated": false,
      "IsXmlType": false,
      "AllowAdditionalFields": false
    },
    {
      "Name": "Route",
      "ImplementationType": "Structure",
      "Description": "route leading to the stop",
      "Fields": [
        {
          "Optional": true,
          "AnyOfTypes": [],
          "AnyOfCasesMeta": [],
          "OneOfTypes": [],
          "OneOfCasesMeta": [],
          "NotTypes": [],
          "NotCasesMeta": [],
          "Type": "Long",
          "IsSdlNativeType": true,
          "IsTypeJsonObject": false,
          "Constant": false,
          "IsStream": false,
          "IsAttribute": false,
          "IsNullExampleExplicit": false,
          "Examples": [],
          "Attributes": {},
          "Nullable": false,
          "NullableArrayItems": false,
          "NullableMapValues": false,
          "ReadOnly": false,
          "WriteOnly": false,
          "IsArray": false,
          "IsMap": false,
          "IsArrayOfMap": false,
          "Deprecated": false,
          "Name": "distance",
          "Description": "route distance in meters",
          "IsNullDefaultExplicit": false
        },
        {
          "Optional": true,
          "AnyOfTypes": [],
          "AnyOfCasesMeta": [],
          "OneOfTypes": [],
          "OneOfCasesMeta": [],
          "NotTypes": [],
          "NotCasesMeta": [],
          "Type": "Long",
          "IsSdlNativeType": true,
          "IsTypeJsonObject": false,
          "Constant": false,
          "IsStream": false,
          "IsAttribute": false,
          "IsNullExampleExplicit": false,
          "Examples": [],
          "Attributes": {},
          "Nullable": false,
          "NullableArrayItems": false,
          "NullableMapValues": false,
          "ReadOnly": false,
          "WriteOnly": false,
          "IsArray": false,
          "IsMap": false,
          "IsArrayOfMap": false,
          "Deprecated": false,
          "Name": "duration",
          "Description": "route duration in seconds",
          "IsNullDefaultExplicit": false
        },
        {
          "Optional": true,
          "AnyOfTypes": [],
          "AnyOfCasesMeta": [],
          "OneOfTypes": [],
          "OneOfCasesMeta": [],
          "NotTypes": [],
          "NotCasesMeta": [],
          "Type": "Mode",
          "IsSdlNativeType": false,
          "Constant": false,
          "IsStream": false,
          "IsAttribute": false,
          "IsNullExampleExplicit": false,
          "Examples": [],
          "Nullable": false,
          "NullableArrayItems": false,
          "NullableMapValues": false,
          "ReadOnly": false,
          "WriteOnly": false,
          "IsArray": false,
          "IsMap": false,
          "IsArrayOfMap": false,
          "Deprecated": false,
          "Name": "mode",
          "Description": "travel mode",
          "IsNullDefaultExplicit": false
        },
        {
          "Optional": true,
          "AnyOfTypes": [],
          "AnyOfCasesMeta": [],
          "OneOfTypes": [],
          "OneOfCasesMeta": [],
          "NotTypes": [],
          "NotCasesMeta": [],
          "Type": "String",
          "IsSdlNativeType": true,
          "IsTypeJsonObject": false,
          "Constant": false,
          "IsStream": false,
          "IsAttribute": false,
          "IsNullExampleExplicit": false,
          "Examples": [],
          "Attributes": {},
          "Nullable": false,
          "NullableArrayItems": false,
          "NullableMapValues": false,
          "ReadOnly": false,
          "WriteOnly": false,
          "IsArray": false,
          "IsMap": false,
          "IsArrayOfMap": false,
          "Deprecated": false,
          "Name": "polyline",
          "Description": "route path compatible with Google polyline encoding algorithm",
          "IsNullDefaultExplicit": false
        }
      ],
      "IsNullExampleExplicit": false,
      "ExampleValues": [],
      "Deprecated": false,
      "IsXmlType": false,
      "AllowAdditionalFields": true
    }
  ],
  "UserDefinedImportedTypes": [
    "Step",
    "Trip"
  ],
  "GlobalTypeCombinators": {},
  "CodeGenSettings": {
    "SynchronyMode": "Asynchronous",
    "ModelSerializationScheme": "Json",
    "ArraySerialization": "Indexed",
    "Nullify404": false,
    "UseHttpMethodPrefix": false,
    "UseModelPrefix": false,
    "UseExceptionPrefix": true,
    "UseEnumPrefix": false,
    "UseControllerPrefix": true,
    "ControllerPostfix": "Api",
    "UseConstructorsForConfig": false,
    "Timeout": 30.0,
    "AndroidUseAppManifest": false,
    "iOSUseAppInfoPlist": false,
    "iOSGenerateCoreData": false,
    "CollapseParamsToArray": false,
    "RunscopeEnabled": false,
    "AndroidHttpClient": "ANDROID_OK",
    "JavaHttpClient": "JAVA_OK",
    "ObjCHttpClient": "UNIREST",
    "CSharpHttpClient": "UNIREST",
    "NodeHttpClient": "NODE_REQUEST",
    "JavaUsePropertiesConfig": false,
    "PHPHttpClient": "UNIREST",
    "EnablePHPComposerVersionString": false,
    "UserAgent": "{language}-SDK/{version} (OS: {os-info}, Engine: {engine}/{engine-version})",
    "EnableGlobalUserAgent": true,
    "EnableAdditionalModelProperties": false,
    "PreserveParameterOrder": true,
    "ValidateRequiredParameters": true,
    "AppendContentHeaders": true,
    "GenerateInterfaces": false,
    "UseCommonSDKLibrary": false,
    "ParameterArrayFormat": "ParamArrayWithIndex",
    "SecurityProtocols": [
      "Ssl3",
      "Tls",
      "Ssl3",
      "Tls"
    ],
    "GenerateTravisConfig": false,
    "GenerateCircleConfig": false,
    "GenerateAppveyorConfig": false,
    "GenerateJenkinsConfig": false,
    "EnableLogging": true,
    "EnableHttpCache": false,
    "Retries": 0,
    "RetryInterval": 1.0,
    "BackoffFactor": 2.0,
    "StatusCodesToRetry": [
      408,
      413,
      429,
      500,
      502,
      503,
      504,
      521,
      522,
      524,
      408,
      413,
      429,
      500,
      502,
      503,
      504,
      521,
      522,
      524
    ],
    "RequestMethodsToRetry": [
      "GET",
      "PUT",
      "GET",
      "PUT"
    ],
    "UserConfigurableRetries": true,
    "GenerateAdvancedDocs": true,
    "DisableDocs": false,
    "StoreTimezoneInformation": false,
    "UnderscoreNumbers": true,
    "UseSingletonPattern": true,
    "IgnoreIfNullJson": false,
    "DisableLinting": false,
    "SortResources": false,
    "ConfigureComponentSorting": {
      "SortEndpointGroups": false,
      "EndpointSorting": "None",
      "SortWebhookGroups": false,
      "SortCallbackGroups": false,
      "WebhookEventsSorting": "None",
      "CallbackEventsSorting": "None",
      "SortModels": false
    },
    "LiftParameterDescriptionFromCustomType": false,
    "AllowSkippingSSLCertVerification": false,
    "ApplyCustomizations": [],
    "DoNotSplitWords": [
      "oauth"
    ],
    "ReturnCompleteHttpResponse": true,
    "ThrowForHttpErrorStatusCodes": true,
    "GenerateModels": true,
    "GenerateEnums": true,
    "GenerateExceptions": true,
    "ResponseMapping": {
      "Type": "Simple"
    },
    "ForceKeywordArgsInRuby": false,
    "SymbolizeHashKeysInRuby": true,
    "UsageExampleEndpoint": {
      "Description": "",
      "EndpointGroupName": "",
      "EndpointName": ""
    },
    "IsLatestVersion": false,
    "CustomDependencies": [],
    "EnableImmutableModels": false,
    "UseEndpointMethodName": false,
    "EncodeTemplateParameters": true,
    "GenerateExamplesForOptionalFields": false,
    "MultitargetDotnetVersions": false,
    "BackoffMax": 0.0,
    "RetryOnTimeout": true,
    "EnableCookies": false,
    "EnableJsonPassThroughForAny": false,
    "PascalCaseEnumForCSharp": false,
    "PascalCaseEnumForTypeScript": false,
    "DisableMultipleAuth": false,
    "AddSingleAuthDeprecatedCode": false,
    "EnableExperimentalTypeCombinatorGeneration": false,
    "UseSecuritySchemeNameForSingleAuth": false,
    "EnableModelKeywordArgsInRuby": true,
    "NullifyEmptyResponses": false,
    "ExtendedAdditionalPropertiesSupport": true,
    "EnforceStandardizedCasing": true,
    "ErrorTemplates": {},
    "GenerateMetadataForTypeScript": false,
    "CSharpSkipEqualityMethods": true,
    "CSharpResolveExceptionPropertyCollisions": true,
    "PhpMapErrorTypesInCompleteResponse": false,
    "GroupEndpointsByMultipleTags": false
  },
  "Errors": [],
  "TestGenSettings": {
    "Configuration": {},
    "TestTimeout": 30,
    "PrecisionDelta": 0.01
  },
  "Namespaces": [],
  "ExternalDocumentation": {
    "Url": "https://help.furkot.com/widgets/furkot-api.html",
    "Description": "Furkot API description"
  },
  "ExportSettings": {
    "ExportExtensions": false,
    "UseDateTimeOnlyInRaml": false,
    "SetPostmanParamValuesAsVariables": false,
    "UseEnvironmentNamesForServerVariables": false,
    "WrapResponseFieldInWsdl": true,
    "AllowEmptyTypeAttributesInXsd": false,
    "WrapInputOutputTypesInElementInXsd": false,
    "AddRefSiblingDataInAllOfSchema": true,
    "EncodeUrlParamsInPostman": true,
    "UseXsdBase64BinaryType": false,
    "ExportXmlMetaData": true,
    "ExportDiscriminatorMappingValues": true,
    "ExportGlobalTypeCombinators": true,
    "ExportAnyType": true,
    "ExportOptionalParametersAsDisabled": false,
    "ExportApiKeyAuthInPostman": true,
    "GenerateSampleValueFromRegexPattern": false,
    "UseHttpMethodPrefixForAutoGeneratedWsdlNames": true,
    "ForceAllowModelExampleExportForSampleGeneration": false
  }
}